__init__.py
bible_search_engine/__init__.py
bible_search_engine/initial_params_niv.json
bible_search_engine/initial_ranker_niv.pkl
bible_search_engine/pipeline.py
bible_search_engine/bible_data/__init__.py
bible_search_engine/bible_data/chapterids_niv.json
bible_search_engine/bible_data/encoded_chapters_niv.npy
bible_search_engine/bible_data/new_testament_niv.jsonl
bible_search_engine/bible_data/old_testament_niv.jsonl
bible_search_engine/bible_index_niv/__init__.py
bible_search_engine/bible_index_niv/chapter_metadata.jsonl
bible_search_engine/bible_index_niv/chapter_vocab.jsonl
bible_search_engine/bible_index_niv/index.jsonl
bible_search_engine/bible_index_niv/statistics.json
bible_search_engine/bible_index_niv/term_metadata.jsonl
bible_search_engine/bible_queries_relevances/README.md
bible_search_engine/bible_queries_relevances/__init__.py
bible_search_engine/bible_queries_relevances/get_train_test_queries.py
bible_search_engine/bible_queries_relevances/predict_relevance.py
bible_search_engine/bible_queries_relevances/test_queries_relevances.csv
bible_search_engine/bible_queries_relevances/train_queries_relevances.csv
bible_search_engine/components/__init__.py
bible_search_engine/components/get_bible_data.py
bible_search_engine/components/indexing.py
bible_search_engine/components/l2r.py
bible_search_engine/components/preprocess.py
bible_search_engine/components/ranker.py
bible_search_engine/components/relevance.py
bible_search_engine-0.2.4.dist-info/LICENSE
bible_search_engine-0.2.4.dist-info/METADATA
bible_search_engine-0.2.4.dist-info/WHEEL
bible_search_engine-0.2.4.dist-info/top_level.txt
bible_search_engine-0.2.4.dist-info/RECORD
