Metadata-Version: 2.1
Name: bible-search-engine
Version: 0.2.4
Summary: Bible search engine incorporating natural language processing, deep learning, and machine learning.
Author-email: Ronen Huang <ronenhuang24@gmail.com>
Project-URL: Homepage, https://github.com/ronenh24/bible_search_engine
Project-URL: Issues, https://github.com/ronenh24/bible_search_engine/issues
Classifier: Programming Language :: Python :: 3
Classifier: Operating System :: OS Independent
Classifier: License :: OSI Approved :: MIT License
Requires-Python: >=3.9
License-File: LICENSE
Requires-Dist: torchvision
Requires-Dist: transformers
Requires-Dist: datasets
Requires-Dist: sentence-transformers
Requires-Dist: spacy
Requires-Dist: spacy-wordnet
Requires-Dist: beautifulsoup4
Requires-Dist: lightgbm
Requires-Dist: optuna
Requires-Dist: fastembed
Requires-Dist: qdrant-client
Requires-Dist: orjson
